.bumpversion.cfg
.gitignore
.travis.yml
LICENSE.txt
MANIFEST.in
README.rst
setup.py
brand/brain.png
brand/favicon.ico
brand/favicon.png
brand/logo.png
brand/logo.svg
brand/swirl_tree.jpg
docs/Makefile
docs/conf.py
docs/index.rst
exmemo/__init__.py
exmemo/collectors.py
exmemo/errors.py
exmemo/plugins.py
exmemo/utils.py
exmemo/workspace.py
exmemo.egg-info/PKG-INFO
exmemo.egg-info/SOURCES.txt
exmemo.egg-info/dependency_links.txt
exmemo.egg-info/entry_points.txt
exmemo.egg-info/requires.txt
exmemo.egg-info/top_level.txt
exmemo/commands/__init__.py
exmemo/commands/cli.py
exmemo/commands/config.py
exmemo/commands/data.py
exmemo/commands/debug.py
exmemo/commands/main.py
exmemo/commands/note.py
exmemo/commands/project.py
exmemo/cookiecutter/__init__.py
exmemo/cookiecutter/cookiecutter.json
exmemo/cookiecutter/hooks/post_gen_project.py
exmemo/cookiecutter/{{cookiecutter.project_slug}}/.exmemorc
exmemo/cookiecutter/{{cookiecutter.project_slug}}/.gitignore
exmemo/cookiecutter/{{cookiecutter.project_slug}}/README.rst
exmemo/cookiecutter/{{cookiecutter.project_slug}}/analysis/.bumpversion.cfg
exmemo/cookiecutter/{{cookiecutter.project_slug}}/analysis/.gitignore
exmemo/cookiecutter/{{cookiecutter.project_slug}}/analysis/.travis.yml
exmemo/cookiecutter/{{cookiecutter.project_slug}}/analysis/MANIFEST.in
exmemo/cookiecutter/{{cookiecutter.project_slug}}/analysis/README.rst
exmemo/cookiecutter/{{cookiecutter.project_slug}}/analysis/setup.py
exmemo/cookiecutter/{{cookiecutter.project_slug}}/analysis/tests/.coveragerc
exmemo/cookiecutter/{{cookiecutter.project_slug}}/analysis/{{cookiecutter.project_slug}}/__init__.py
exmemo/cookiecutter/{{cookiecutter.project_slug}}/notebook/.gitignore
exmemo/cookiecutter/{{cookiecutter.project_slug}}/notebook/Makefile
exmemo/cookiecutter/{{cookiecutter.project_slug}}/notebook/conf.py
exmemo/cookiecutter/{{cookiecutter.project_slug}}/notebook/ideas_and_feedback.rst
exmemo/cookiecutter/{{cookiecutter.project_slug}}/notebook/index.rst
exmemo/cookiecutter/{{cookiecutter.project_slug}}/notebook/unexpected_observations.rst
exmemo/sphinx/__init__.py
exmemo/sphinx/biology.py
exmemo/sphinx/favicon.ico
exmemo/sphinx/general.py
