Metadata-Version: 1.1
Name: exmemo
Version: 0.3.0
Summary: UNKNOWN
Home-page: https://github.com/kalekundert/exmemo
Author: Kale Kundert
Author-email: kale@thekunderts.net
License: UNKNOWN
Platform: UNKNOWN
Classifier: Topic :: Scientific/Engineering
Classifier: Intended Audience :: Science/Research
Classifier: Programming Language :: Python :: 3.6
Classifier: License :: OSI Approved :: GNU General Public License v3 (GPLv3)
Classifier: Development Status :: 2 - Pre-Alpha
